odoo/addons/l10n_fr_pos_cert_update_draft_order_line/README.rst
odoo/addons/l10n_fr_pos_cert_update_draft_order_line/__init__.py
odoo/addons/l10n_fr_pos_cert_update_draft_order_line/__manifest__.py
odoo/addons/l10n_fr_pos_cert_update_draft_order_line/i18n/l10n_fr_pos_cert_update_draft_order_line.pot
odoo/addons/l10n_fr_pos_cert_update_draft_order_line/readme/CONTRIBUTORS.rst
odoo/addons/l10n_fr_pos_cert_update_draft_order_line/readme/DESCRIPTION.rst
odoo/addons/l10n_fr_pos_cert_update_draft_order_line/static/description/icon.png
odoo/addons/l10n_fr_pos_cert_update_draft_order_line/static/description/index.html
odoo/addons/l10n_fr_pos_cert_update_draft_order_line/static/src/js/models.js
odoo_addon_l10n_fr_pos_cert_update_draft_order_line-16.0.1.0.1.dist-info/METADATA
odoo_addon_l10n_fr_pos_cert_update_draft_order_line-16.0.1.0.1.dist-info/WHEEL
odoo_addon_l10n_fr_pos_cert_update_draft_order_line-16.0.1.0.1.dist-info/top_level.txt
odoo_addon_l10n_fr_pos_cert_update_draft_order_line-16.0.1.0.1.dist-info/RECORD
