Metadata-Version: 2.1
Name: odoo-addon-l10n-fr-pos-cert-update-draft-order-line
Version: 16.0.1.0.1
Summary: fixes the French certification module implemented by Odoo, authorizing the modification of draft sales lines.
Home-page: https://github.com/OCA/l10n-france
Author: GRAP,Odoo Community Association (OCA)
Author-email: support@odoo-community.org
License: LGPL-3
Platform: UNKNOWN
Classifier: Programming Language :: Python
Classifier: Framework :: Odoo
Classifier: Framework :: Odoo :: 16.0
Classifier: License :: OSI Approved :: GNU Lesser General Public License v3 (LGPLv3)
Requires-Python: >=3.10
Requires-Dist: odoo <16.1dev,>=16.0a
